cache/__init__.py
cache/expiringcache.py
expiring_cache-1.0.0.dist-info/LICENSE
expiring_cache-1.0.0.dist-info/METADATA
expiring_cache-1.0.0.dist-info/WHEEL
expiring_cache-1.0.0.dist-info/top_level.txt
expiring_cache-1.0.0.dist-info/RECORD
