Metadata-Version: 2.1
Name: expiring-cache
Version: 1.0.0
Summary: A simple Python dict with TTL support for auto-expiring caches with support for case-insensitive keys.
Home-page: https://github.com/ItsArtemiz/expiring-cache
Author: ItsArtemiz
License: MIT
Platform: UNKNOWN
Classifier: Development Status :: 5 - Production/Stable
Classifier: License :: OSI Approved :: MIT License
Classifier: Intended Audience :: Developers
Classifier: Natural Language :: English
Classifier: Operating System :: OS Independent
Classifier: Programming Language :: Python :: 3.7
Classifier: Topic :: Software Development :: Libraries
Classifier: Topic :: Software Development :: Libraries :: Python Modules
Classifier: Topic :: Utilities
Requires-Python: >3.7.0
License-File: LICENSE
